jupyter_MyBash_kernel/IMyKernel.py
jupyter_MyBash_kernel/MyKernel.py
jupyter_MyBash_kernel/MyMagics.py
jupyter_MyBash_kernel/Mymacroprocessor.py
jupyter_MyBash_kernel/__init__.py
jupyter_MyBash_kernel/__main__.py
jupyter_MyBash_kernel/install_MyBash_kernel
jupyter_MyBash_kernel/ipynbfile.py
jupyter_MyBash_kernel/kernel.py
jupyter_MyBash_kernel/plugins/CDnotes.py
jupyter_MyBash_kernel/plugins/ISpecialID.py
jupyter_MyBash_kernel/plugins/MyMDDFile.py
jupyter_MyBash_kernel/plugins/MyRunGDB.py
jupyter_MyBash_kernel/plugins/Pdefine.py
jupyter_MyBash_kernel/plugins/__init__.py
jupyter_MyBash_kernel/plugins/_filter2_magics.py
jupyter_MyBash_kernel/plugins/ccompiler.py
jupyter_MyBash_kernel/plugins/dartcommand.py
jupyter_MyBash_kernel/plugins/define.py
jupyter_MyBash_kernel/plugins/env.py
jupyter_MyBash_kernel/plugins/execfile.py
jupyter_MyBash_kernel/plugins/file.py
jupyter_MyBash_kernel/plugins/filedict.py
jupyter_MyBash_kernel/plugins/filefordict.py
jupyter_MyBash_kernel/plugins/fileforlist.py
jupyter_MyBash_kernel/plugins/filelist.py
jupyter_MyBash_kernel/plugins/fluttercommand.py
jupyter_MyBash_kernel/plugins/include.py
jupyter_MyBash_kernel/plugins/ipynbfile.py
jupyter_MyBash_kernel/plugins/kcommand.py
jupyter_MyBash_kernel/plugins/mytest.py
jupyter_MyBash_kernel/plugins/noruncode.py
jupyter_MyBash_kernel/plugins/onlycompile.py
jupyter_MyBash_kernel/plugins/onlycsfile.py
jupyter_MyBash_kernel/plugins/onlyruncmd.py
jupyter_MyBash_kernel/plugins/onlyrungcc.py
jupyter_MyBash_kernel/plugins/onlyrunnotecmd.py
jupyter_MyBash_kernel/plugins/overwritefile.py
jupyter_MyBash_kernel/plugins/ptemplate.py
jupyter_MyBash_kernel/plugins/pubcommand.py
jupyter_MyBash_kernel/plugins/pycommand.py
jupyter_MyBash_kernel/plugins/shellcommand.py
jupyter_MyBash_kernel/plugins/showpid.py
jupyter_MyBash_kernel/plugins/templatefile.py
jupyter_MyBash_kernel-0.0.1.data/scripts/install_MyBash_kernel
jupyter_MyBash_kernel-0.0.1.dist-info/LICENSE
jupyter_MyBash_kernel-0.0.1.dist-info/LICENSE.txt
jupyter_MyBash_kernel-0.0.1.dist-info/METADATA
jupyter_MyBash_kernel-0.0.1.dist-info/WHEEL
jupyter_MyBash_kernel-0.0.1.dist-info/top_level.txt
jupyter_MyBash_kernel-0.0.1.dist-info/RECORD
