Metadata-Version: 2.1
Name: jupyter-MyBash-kernel
Version: 0.0.1
Summary: Minimalistic shellscript kernel for Jupyter
Home-page: https://github.com/nufeng1999/jupyter-MyBash-kernel/
Author: nufeng
Author-email: 18478162@qq.com
License: MIT
Download-URL: https://github.com/nufeng1999/jupyter-MyBash-kernel/releases/tag/0.0.1
Keywords: jupyter,notebook,kernel,shell,shellscript,Bash,sh
Platform: UNKNOWN
Classifier: Programming Language :: Python :: 3
Classifier: License :: OSI Approved :: MIT License
Classifier: Operating System :: OS Independent
License-File: LICENSE
License-File: LICENSE.txt
